CloudStack-3.0.0.1.dist-info/WHEEL
CloudStack-3.0.0.1.dist-info/DESCRIPTION.rst
CloudStack-3.0.0.1.dist-info/pydist.json
CloudStack-3.0.0.1.dist-info/METADATA
CloudStack-3.0.0.1.dist-info/top_level.txt
CloudStack-3.0.0.1.dist-info/RECORD
Users/larstobi/Library/Python/2.7/site-packages/CloudStack/ExtendedClient.py
Users/larstobi/Library/Python/2.7/site-packages/CloudStack/BaseClient.py
Users/larstobi/Library/Python/2.7/site-packages/CloudStack/Client.py
Users/larstobi/Library/Python/2.7/site-packages/CloudStack/__init__.py
