Metadata-Version: 2.0
Name: CloudStack
Version: 3.0.0.1
Summary: CloudStack API v2.2 Client
Home-page: https://github.com/larstobi/cloudstack-python-client
Author: Jason Hancock
Author-email: jsnbyh@gmail.com
License: MIT
Platform: Posix; MacOS X; Windows
